<b name="2 John" acr="2jo" nc="1">
  <c num="1">
    <v num="1" txt="O ancião à senhora eleita, e a seus filhos, aos quais eu amo em verdade, e não somente eu, mas também todos os que conhecem a verdade,"/>
    <v num="2" txt="por causa da verdade que permanece em nós, e para sempre estará conosco:"/>
    <v num="3" txt="Graça, misericórdia, paz, da parte de Deus Pai e da parte de Jesus Cristo, o Filho do Pai, serão conosco em verdade e amor."/>
    <v num="4" txt="Muito me alegro por ter achado alguns de teus filhos andando na verdade, assim como recebemos mandamento do Pai."/>
    <v num="5" txt="E agora, senhora, rogo-te, não como te escrevendo um novo mandamento, mas aquele mesmo que desde o princípio tivemos: que nos amemos uns aos outros."/>
    <v num="6" txt="E o amor é este: que andemos segundo os seus mandamentos. Este é o mandamento, como já desde o princípio ouvistes, para que nele andeis."/>
    <v num="7" txt="Porque já muitos enganadores saíram pelo mundo, os quais não confessam que Jesus Cristo veio em carne. Tal é o enganador e o anticristo."/>
    <v num="8" txt="Olhai por vós mesmos, para que não percais o fruto do nosso trabalho, antes recebeis plena recompensa."/>
    <v num="9" txt="Todo aquele que vai além do ensino de Cristo e não permanece nele, não tem a Deus; quem permanece neste ensino, esse tem tanto ao Pai como ao Filho."/>
    <v num="10" txt="Se alguém vem ter convosco, e não traz este ensino, não o recebais em casa, nem tampouco o saudeis."/>
    <v num="11" txt="Porque quem o saúda participa de suas más obras."/>
    <v num="12" txt="Embora tenha eu muitas coisas para vos escrever, não o quis fazer com papel e tinta; mas espero visitar-vos e falar face a face, para que o nosso gozo seja completo."/>
    <v num="13" txt="Saúdam-te os filhos de tua irmã, a eleita."/>
  </c>
</b>